Metadata-Version: 2.4
Name: singer-encodings
Version: 0.3.0
Summary: Singer.io encodings library
Home-page: http://singer.io
Author: Stitch
Classifier: Programming Language :: Python :: 3 :: Only
License-File: LICENSE
Requires-Dist: singer-python
Requires-Dist: pyarrow==21.0.0
Requires-Dist: fastavro==1.12.0
Provides-Extra: dev
Requires-Dist: pytest; extra == "dev"
Dynamic: author
Dynamic: classifier
Dynamic: home-page
Dynamic: license-file
Dynamic: provides-extra
Dynamic: requires-dist
Dynamic: summary
